detect_anomalies_package/__init__.py
detect_anomalies_package/detect_anomalies.py
tests/__init__.py
tests/test_detect_anomalies.py
detect_anomalies_package-0.0.2.dist-info/LICENSE
detect_anomalies_package-0.0.2.dist-info/METADATA
detect_anomalies_package-0.0.2.dist-info/WHEEL
detect_anomalies_package-0.0.2.dist-info/top_level.txt
detect_anomalies_package-0.0.2.dist-info/RECORD
