Metadata-Version: 2.1
Name: detect-anomalies-package
Version: 0.0.2
Summary: A Python package for anomaly detection using various techniques.
Home-page: UNKNOWN
Author: Nikhil Mugganawar
Author-email: nikhil.mugganawar@gmail.com
License: MIT
Platform: UNKNOWN
Requires-Dist: numpy
Requires-Dist: scipy
Requires-Dist: scikit-learn
